uhooapi/__init__.py
uhooapi/api.py
uhooapi/client.py
uhooapi/const.py
uhooapi/device.py
uhooapi/endpoints.py
uhooapi/errors.py
uhooapi/util.py
uhooapi-1.2.6.dist-info/licenses/LICENSE
uhooapi-1.2.6.dist-info/METADATA
uhooapi-1.2.6.dist-info/WHEEL
uhooapi-1.2.6.dist-info/top_level.txt
uhooapi-1.2.6.dist-info/RECORD
