Metadata-Version: 2.4
Name: uhooapi
Version: 1.2.6
Summary: A python client for uHoo APIs
Author-email: Joshua Monta <joshsmonta@gmail.com>
Project-URL: Homepage, https://github.com/getuhoo/uhooapi
Project-URL: Bug Tracker, https://github.com/getuhoo/uhooapi/issues
Classifier: Programming Language :: Python :: 3
Classifier: Programming Language :: Python :: 3.13
Classifier: Programming Language :: Python :: 3.14
Classifier: License :: OSI Approved :: MIT License
Classifier: Operating System :: OS Independent
Requires-Python: >=3.13
License-File: LICENSE
Requires-Dist: aiohttp<4.0,>=3.13.2
Provides-Extra: dev
Requires-Dist: pytest>=7.0.0; extra == "dev"
Requires-Dist: pytest-asyncio>=0.21.0; extra == "dev"
Requires-Dist: pytest-cov>=4.0.0; extra == "dev"
Requires-Dist: pytest-aiohttp>=1.0.0; extra == "dev"
Requires-Dist: pytest-mock>=3.10.0; extra == "dev"
Requires-Dist: aioresponses>=0.7.0; extra == "dev"
Requires-Dist: black>=23.0.0; extra == "dev"
Requires-Dist: isort>=5.12.0; extra == "dev"
Requires-Dist: flake8>=6.0.0; extra == "dev"
Requires-Dist: mypy>=1.0.0; extra == "dev"
Requires-Dist: tomli>=2.3.0; extra == "dev"
Dynamic: license-file
